tensorblob/__init__.py
tensorblob/_blob.py
tensorblob-0.1.2.dist-info/METADATA
tensorblob-0.1.2.dist-info/WHEEL
tensorblob-0.1.2.dist-info/licenses/LICENSE
tensorblob-0.1.2.dist-info/RECORD
