Metadata-Version: 2.4
Name: tensorblob
Version: 0.1.2
Summary: Lightweight, dynamic-sized, memory-mapped tensor storage with file-like APIs.
Author-email: guest400123064 <wangy49@seas.upenn.edu>
License:                                  Apache License
License-File: LICENSE
Requires-Python: >=3.10
Requires-Dist: just-config-mixin>=0.1.1rc2
Requires-Dist: tensordict>=0.10.0
